{
  "_grid": "grid/gridOffset — РЕАЛЬНАЯ сетка весов в зале. Допустимы только веса gridOffset + k*grid. Стек тренажёров: grid 5, ровные числа (10/15/20). Жим ногами: grid 5 со смещением 2.5 (62.5/67.5/72.5). Гантели: grid 2. build.mjs округляет вычисленный прирост ВВЕРХ до ближайшего доступного веса — назначать 17.5 кг там, где есть только 15 и 20, нельзя.",
  "_": "Программа. Веса сюда НЕ пишутся — они подтягиваются из журнала тренировок в базе знаний (~/Knowledge/Здоровье/Владимир/Журнал тренировок/). Здесь только упражнения, техника и правила прогрессии.",
  "warmup": [
    "Лёгкое кардио — 5 мин. Дорожка/вело. Поднять пульс, не устать.",
    "Кошка-корова — 10 раз. Мягко, медленно. Готовит поясницу.",
    "Разведения с резинкой — 15–20. Активируют плечо ДО нагрузки."
  ],
  "days": {
    "A": [
      {
        "n": 1, "name": "Тяга с упором в грудь", "photo": "p3",
        "sets": 4, "reps": "10–12", "repMin": 10, "repMax": 12, "rest": 90,
        "step": 2.5, "grid": 2.5, "gridOffset": 0, "startIfNone": 8,
        "cues": [
          "Грудь и рука лежат на наклонной скамье — <b>поясница разгружена</b>.",
          "Тянешь <b>локтем назад</b>, сводишь лопатку."
        ],
        "video": "тяга+гантели+с+упором+в+скамью"
      },
      {
        "n": 2, "name": "Жим в тренажёре на грудь", "photo": "p4",
        "sets": 3, "reps": "10–12", "repMin": 10, "repMax": 12, "rest": 90,
        "step": 2.5, "grid": 5, "gridOffset": 0, "startIfNone": 15,
        "warn": "Если тренажёр стоит в режиме жима <b>над головой</b> — этот режим не использовать. Только горизонтальный жим от груди. Плечо.",
        "cues": [
          "Жать <b>вперёд на уровне груди</b>, не над головой.",
          "Локти ~45°, не уводить за спину в глубокую растяжку."
        ],
        "video": "жим+в+тренажёре+на+грудь+сидя"
      },
      {
        "n": 3, "name": "Жим ногами", "photo": "p6",
        "sets": 3, "reps": "10–12", "repMin": 10, "repMax": 12, "rest": 120,
        "step": 7.5, "grid": 7.5, "gridOffset": 5, "startIfNone": 57.5,
        "cues": [
          "Поясницу и таз <b>не отрывать</b> от спинки — главное правило для твоей спины.",
          "Колени по линии стоп, вверху <b>не разгибать в замок</b>.",
          "Не опускать платформу так глубоко, что таз скручивается."
        ],
        "video": "жим+ногами+в+тренажёре+техника"
      },
      {
        "n": 4, "name": "Тяга верхнего блока", "photo": "p5",
        "sets": 4, "reps": "10–12", "repMin": 10, "repMax": 12, "rest": 90,
        "step": 2.5, "grid": 5, "gridOffset": 0, "startIfNone": 15,
        "cues": [
          "Тянуть <b>к верху груди</b>, не за голову.",
          "<b>Нейтральный</b> (параллельный) или узкий хват — бережёт сустав.",
          "Не откидывать корпус назад рывком."
        ],
        "video": "тяга+верхнего+блока+нейтральный+хват"
      },
      {
        "n": 5, "name": "Разгибание на трицепс у блока (канат)", "photo": "p1",
        "sets": 3, "reps": "12–15", "repMin": 12, "repMax": 15, "rest": 60,
        "step": 2.5, "grid": 5, "gridOffset": 0, "startIfNone": 15,
        "cues": [
          "<b>Локти прижаты к бокам</b> и не двигаются. Работает только предплечье.",
          "Тянешь канат <b>вниз</b>. Рука перед корпусом — плечу безопасно."
        ],
        "video": "разгибание+на+трицепс+у+блока+канат+техника"
      },
      {
        "n": 6, "name": "Сгибание на бицепс с гантелями", "photo": null,
        "sets": 3, "reps": "12–15", "repMin": 12, "repMax": 15, "rest": 60,
        "step": 2, "grid": 2, "gridOffset": 0, "startIfNone": 8,
        "note": "Перенесено из дня B (21.07): там стояло после махов без связи с соседями, здесь идёт за трицепсом — руки блоком, изоляция в конце, и обе тяги дня уже прогрели бицепс.",
        "cues": [
          "<b>Локти прижаты к бокам</b>, корпусом не помогаешь, без раскачки.",
          "Рука работает <b>перед корпусом и внизу</b> — плечу безопасно."
        ],
        "video": "сгибание+на+бицепс+с+гантелями+техника"
      },
      {
        "n": 7, "name": "Сгибание ног", "photo": "p9",
        "sets": 3, "reps": "12–15", "repMin": 12, "repMax": 15, "rest": 75,
        "step": 2.5, "grid": 5, "gridOffset": 0, "startIfNone": 25,
        "cues": [
          "Бицепс бедра — компенсирует отсутствие становой.",
          "Без рывков, контролируй негативную фазу."
        ],
        "video": "сгибание+ног+в+тренажёре"
      },
      {
        "n": 8, "name": "Чемоданная стойка (статика, на месте)", "photo": null,
        "sets": 3, "reps": "30–40 сек / сторону", "repMin": 0, "repMax": 0, "rest": 60,
        "step": 2, "grid": 2, "gridOffset": 0, "startIfNone": 12,
        "note": "Заменила чемоданную переноску (21.07): для проходки 20–30 м в зале нет места, упражнение пропущено дважды подряд. Нагрузка на косые та же — гантель тянет вбок, кор её держит, — но без единого шага. Кранч и подъёмы ног по-прежнему запрещены (сгибание позвоночника), Pallof владелец отверг.",
        "cues": [
          "Тяжёлая гантель <b>в одной руке</b>, стоишь на месте 30–40 сек. Потом вторая сторона.",
          "Гантель тянет вбок — <b>держишь плечи и таз ровно</b>, не заваливаться. В этом вся работа пресса.",
          "Поясница нейтральна, дышишь ровно. Рука висит у бедра — плечу безопасно.",
          "Дошёл до 40 сек чисто на обе стороны — <b>+2 кг</b>, а не больше секунд."
        ],
        "video": "чемоданная+стойка+suitcase+hold+техника"
      }
    ],
    "B": [
      {
        "n": 1, "name": "Жим ногами, стопы выше", "photo": "p6",
        "sets": 3, "reps": "10–12", "repMin": 10, "repMax": 12, "rest": 120,
        "step": 7.5, "grid": 7.5, "gridOffset": 5, "startIfNone": 57.5,
        "cues": [
          "Стопы <b>выше и шире</b> на платформе — акцент на ягодицы и бицепс бедра.",
          "Поясницу не отрывать, колени не в замок."
        ],
        "video": "жим+ногами+стопы+высоко+ягодицы"
      },
      {
        "n": 2, "name": "Жим гантелей на наклонной 30°", "photo": null,
        "sets": 3, "reps": "10–12", "repMin": 10, "repMax": 12, "rest": 90,
        "step": 2, "grid": 2, "gridOffset": 0, "startIfNone": 8,
        "warn": "Плечо. В нижней точке рука уходит <b>назад</b> — в опасную позицию. <b>Глубина под запретом</b>: короче амплитуда, легче вес.",
        "cues": [
          "<b>ЖИМ — толкаешь гантели вверх от груди</b>, НЕ тянешь к себе. Работает грудь.",
          "Хват <b>нейтральный</b> (ладони друг к другу), локти прижаты ~45°.",
          "<b>Не опускать ниже линии груди.</b> Амплитуду режем намеренно."
        ],
        "video": "жим+гантелей+нейтральным+хватом+наклонная"
      },
      {
        "n": 3, "name": "Горизонтальная тяга сидя", "photo": "p5",
        "sets": 4, "reps": "10–12", "repMin": 10, "repMax": 12, "rest": 90,
        "step": 2.5, "grid": 5, "gridOffset": 0, "startIfNone": 20,
        "note": "Поднята с 4-го места на 3-е (21.07): компаунд должен идти раньше изоляции. Четвёртый подход добавлен там же — тяга к жиму выходит 2:1, как рекомендуют при истории вывиха плеча.",
        "cues": [
          "Корпус <b>прямой и зафиксирован</b>, не раскачивать поясницей.",
          "Тянешь к животу, сводишь лопатки. Нейтральный хват."
        ],
        "video": "горизонтальная+тяга+сидя+техника"
      },
      {
        "n": 4, "name": "Разведение бёдер (Abduction)", "photo": "p7",
        "sets": 3, "reps": "15", "repMin": 15, "repMax": 15, "rest": 60,
        "step": 2.5, "grid": 5, "gridOffset": 0, "startIfNone": 20,
        "cues": [
          "Режим <b>ABDUCTION</b> — ноги разводишь. Средняя ягодичная.",
          "Крепкие ягодицы разгружают поясницу — это работа на твою спину."
        ],
        "video": "разведение+бедер+в+тренажёре"
      },
      {
        "n": 5, "name": "Махи гантелями в стороны", "photo": null,
        "sets": 3, "reps": "12–15", "repMin": 12, "repMax": 15, "rest": 60,
        "step": 2, "grid": 2, "gridOffset": 0, "startIfNone": 6,
        "warn": "Плечо. Подъём до уровня плеч и выше — запрещён. Амплитуда урезана намеренно.",
        "cues": [
          "<b>Не выше 60°</b> — до середины между поясом и плечом. Не до горизонта.",
          "Большой палец вверх, без рывка. <b>Лёгкий вес.</b>"
        ],
        "video": "махи+гантелями+в+стороны+техника"
      },
      {
        "n": 6, "name": "Сгибание ног", "photo": "p9",
        "sets": 3, "reps": "12–15", "repMin": 12, "repMax": 15, "rest": 75,
        "step": 2.5, "grid": 5, "gridOffset": 0, "startIfNone": 25,
        "cues": ["Да, как в Дне A. Единственный безопасный для твоей спины вариант — повтор намеренный."],
        "video": "сгибание+ног+в+тренажёре"
      },
      {
        "n": 7, "name": "Гиперэкстензия", "photo": null,
        "sets": 3, "reps": "12", "repMin": 12, "repMax": 12, "rest": 60,
        "step": 0, "startIfNone": 0,
        "note": "По просьбе владельца (17.07). Разнесена с боковой планкой на отдельные упражнения 21.07 — это разные движения с разным отдыхом.",
        "cues": [
          "<b>Без веса.</b> Поднимаешься <b>не выше нейтрали</b> — не выгибаться вверх. При остеохондрозе переразгибание под запретом.",
          "Медленно, без рывка. Работают ягодицы и разгибатели, а не рывок поясницей.",
          "Внизу не круглить спину — опускаешься ровно настолько, насколько держишь нейтраль."
        ],
        "video": "гиперэкстензия+без+веса+техника"
      },
      {
        "n": 8, "name": "Боковая планка", "photo": null,
        "sets": 3, "reps": "20–30 сек / сторону", "repMin": 0, "repMax": 0, "rest": 45,
        "step": 0, "startIfNone": 0,
        "note": "Стабилизация кора. Осталась от связки с dead bug (тот убран 17.07 — в зале некомфортно). Разнесена с гиперэкстензией 21.07.",
        "cues": [
          "Упор на предплечье, <b>тело прямой линией</b> от пятки до макушки. Таз не проваливать.",
          "Опорное плечо <b>под локтем</b>, не заваливаться на сустав — плечо.",
          "20–30 сек на сторону, дышишь ровно. Тяжело — сократи время, но не ломай линию."
        ],
        "video": "боковая+планка+техника"
      }
    ]
  }
}
